bigone/__init__.py
bigone/base.py
bigone/client.py
bigone_sdk_py-0.0.2.dist-info/LICENSE
bigone_sdk_py-0.0.2.dist-info/METADATA
bigone_sdk_py-0.0.2.dist-info/WHEEL
bigone_sdk_py-0.0.2.dist-info/top_level.txt
bigone_sdk_py-0.0.2.dist-info/RECORD
